countdoom/__init__.py
countdoom/__main__.py
countdoom/cli.py
countdoom/client.py
countdoom-0.2.1.dist-info/AUTHORS.md
countdoom-0.2.1.dist-info/LICENSE
countdoom-0.2.1.dist-info/METADATA
countdoom-0.2.1.dist-info/WHEEL
countdoom-0.2.1.dist-info/entry_points.txt
countdoom-0.2.1.dist-info/top_level.txt
countdoom-0.2.1.dist-info/RECORD
