Metadata-Version: 2.1
Name: countdoom
Version: 0.2.1
Summary: Fetch the current Doomsday Clock from TheBulletin.org
Home-page: https://github.com/renemarc/countdoom
Author: René-Marc Simard
Author-email: renemarc@gmail.com
License: MIT license
Project-URL: Documentation, https://countdoom.readthedocs.io/
Project-URL: Changelog, https://countdoom.readthedocs.io/en/latest/changelog.html
Project-URL: Issue Tracker, https://github.com/renemarc/countdoom/issues
Keywords: Doomsday,Clock
Platform: UNKNOWN
Classifier: Development Status :: 3 - Alpha
Classifier: Environment :: Console
Classifier: Intended Audience :: Developers
Classifier: Intended Audience :: End Users/Desktop
Classifier: License :: OSI Approved :: MIT License
Classifier: Natural Language :: English
Classifier: Programming Language :: Python :: 3
Classifier: Programming Language :: Python :: 3.5
Classifier: Programming Language :: Python :: 3.6
Classifier: Programming Language :: Python :: 3.7
Classifier: Programming Language :: Python :: 3.8
Classifier: Programming Language :: Python :: Implementation :: PyPy
Classifier: Topic :: Internet :: WWW/HTTP
Classifier: Topic :: Software Development :: Libraries :: Python Modules
Requires-Python: >=3.5
Requires-Dist: aiohttp (<4.0)
Requires-Dist: beautifulsoup4
Provides-Extra: dev
Requires-Dist: aioresponses ; extra == 'dev'
Requires-Dist: argh ; extra == 'dev'
Requires-Dist: bandit ; extra == 'dev'
Requires-Dist: black ; extra == 'dev'
Requires-Dist: bump2version ; extra == 'dev'
Requires-Dist: check-manifest ; extra == 'dev'
Requires-Dist: codecov ; extra == 'dev'
Requires-Dist: coverage ; extra == 'dev'
Requires-Dist: flake8 ; extra == 'dev'
Requires-Dist: flake8-isort ; extra == 'dev'
Requires-Dist: git-pylint-commit-hook ; extra == 'dev'
Requires-Dist: isort ; extra == 'dev'
Requires-Dist: m2r ; extra == 'dev'
Requires-Dist: mypy ; extra == 'dev'
Requires-Dist: pre-commit ; extra == 'dev'
Requires-Dist: pylint ; extra == 'dev'
Requires-Dist: pytest ; extra == 'dev'
Requires-Dist: pytest-asyncio ; extra == 'dev'
Requires-Dist: pytest-httpserver ; extra == 'dev'
Requires-Dist: pytoml ; extra == 'dev'
Requires-Dist: requests ; extra == 'dev'
Requires-Dist: setuptools ; extra == 'dev'
Requires-Dist: Sphinx ; extra == 'dev'
Requires-Dist: sphinx-autodoc-typehints ; extra == 'dev'
Requires-Dist: sphinx-rtd-theme ; extra == 'dev'
Requires-Dist: toml ; extra == 'dev'
Requires-Dist: tox (>=2.4) ; extra == 'dev'
Requires-Dist: twine ; extra == 'dev'
Requires-Dist: watchdog ; extra == 'dev'
Requires-Dist: wheel ; extra == 'dev'
Provides-Extra: dist
Requires-Dist: bandit ; extra == 'dist'
Requires-Dist: bump2version ; extra == 'dist'
Requires-Dist: check-manifest ; extra == 'dist'
Requires-Dist: flake8 ; extra == 'dist'
Requires-Dist: flake8-isort ; extra == 'dist'
Requires-Dist: git-pylint-commit-hook ; extra == 'dist'
Requires-Dist: pre-commit ; extra == 'dist'
Requires-Dist: pylint ; extra == 'dist'
Requires-Dist: pytoml ; extra == 'dist'
Requires-Dist: setuptools ; extra == 'dist'
Requires-Dist: twine ; extra == 'dist'
Requires-Dist: wheel ; extra == 'dist'
Provides-Extra: docs
Requires-Dist: argh ; extra == 'docs'
Requires-Dist: m2r ; extra == 'docs'
Requires-Dist: Sphinx ; extra == 'docs'
Requires-Dist: sphinx-autodoc-typehints ; extra == 'docs'
Requires-Dist: sphinx-rtd-theme ; extra == 'docs'
Requires-Dist: watchdog ; extra == 'docs'
Provides-Extra: lint
Requires-Dist: flake8 ; extra == 'lint'
Requires-Dist: flake8-isort ; extra == 'lint'
Requires-Dist: isort ; extra == 'lint'
Requires-Dist: mypy ; extra == 'lint'
Requires-Dist: pylint ; extra == 'lint'
Requires-Dist: toml ; extra == 'lint'
Requires-Dist: black ; extra == 'lint'
Provides-Extra: test
Requires-Dist: aioresponses ; extra == 'test'
Requires-Dist: codecov ; extra == 'test'
Requires-Dist: coverage ; extra == 'test'
Requires-Dist: pytest ; extra == 'test'
Requires-Dist: pytest-asyncio ; extra == 'test'
Requires-Dist: pytest-httpserver ; extra == 'test'
Requires-Dist: requests ; extra == 'test'
Requires-Dist: tox (>=2.4) ; extra == 'test'
